setup.py
bdist_mpkg/__init__.py
bdist_mpkg/cmd_bdist_mpkg.py
bdist_mpkg/pkg.py
bdist_mpkg/plists.py
bdist_mpkg/script_bdist_mpkg.py
bdist_mpkg/templates.py
bdist_mpkg/tools.py
bdist_mpkg/util.py
bdist_mpkg.egg-info/PKG-INFO
bdist_mpkg.egg-info/SOURCES.txt
bdist_mpkg.egg-info/entry_points.txt
bdist_mpkg.egg-info/top_level.txt
bdist_mpkg.egg-info/zip-safe
ez_setup/README.txt
ez_setup/__init__.py
