Metadata-Version: 1.0
Name: bdist_mpkg
Version: 0.4
Summary: Builds Mac OS X installer packages from distutils
Home-page: http://undefined.org/python/#bdist_mpkg
Author: Bob Ippolito
Author-email: bob@redivi.com
License: MIT License
Platform: any
Classifier: Intended Audience :: Developers
Classifier: License :: OSI Approved :: MIT License
Classifier: Programming Language :: Python
Classifier: Operating System :: MacOS :: MacOS X
Classifier: Topic :: Software Development :: Libraries :: Python Modules
Classifier: Topic :: Software Development :: Build Tools
